statsnz/__init__.py
statsnz-1.0.7.dist-info/METADATA
statsnz-1.0.7.dist-info/WHEEL
statsnz-1.0.7.dist-info/entry_points.txt
statsnz-1.0.7.dist-info/top_level.txt
statsnz-1.0.7.dist-info/RECORD
