Metadata-Version: 1.1
Name: statsnz
Version: 1.0.7
Summary: A collection of functions to enable ease of use of the various Stats NZ APIs
Home-page: https://github.com/basanovase/statsnz
Author: Flynn
Author-email: flynn.mclean@gmail.com
License: MIT
Platform: UNKNOWN
Classifier: License :: OSI Approved :: MIT License
Classifier: Programming Language :: Python :: 3
Classifier: Programming Language :: Python :: 3.8
